dotstree/__init__.py
dotstree/lib.py
dotstree/main.py
dotstree-0.1.6.dist-info/METADATA
dotstree-0.1.6.dist-info/WHEEL
dotstree-0.1.6.dist-info/entry_points.txt
dotstree-0.1.6.dist-info/top_level.txt
dotstree-0.1.6.dist-info/RECORD
