Metadata-Version: 2.1
Name: dotstree
Version: 0.1.6
Summary: Flexible dotfile manager based on directory trees.
Home-page: https://www.github.com/metov/dotstree
Author: Azat Akhmetov
Author-email: azatinfo@yandex.com
Requires-Dist: coloredlogs
Requires-Dist: docopt
Requires-Dist: metovlogs
Requires-Dist: PyYAML
Requires-Dist: questionary
Requires-Dist: tabulate
Requires-Dist: tqdm
